selnetime/__init__.py
selnetime/bins.py
selnetime/hmm.py
selnetime/moments.py
selnetime/sim_cmd.py
selnetime/simulator.py
selnetime/snt.py
selnetime/utils.py
selnetime-0.3.2.dist-info/METADATA
selnetime-0.3.2.dist-info/WHEEL
selnetime-0.3.2.dist-info/entry_points.txt
selnetime-0.3.2.dist-info/top_level.txt
selnetime-0.3.2.dist-info/RECORD
