Metadata-Version: 2.1
Name: selnetime
Version: 0.3.2
Summary: Implementation of HMM to estimate selection and demography
Author-email: Mathieu Uhl <mathieu.uhl@cefe.cnrs.fr>, Paul Bunel <paul.bunel@inrae.fr>, Simon Boitard <simon.boitard@inrae.fr>, Miguel de Navascués <miguel.navascues@inrae.fr>, Bertrand Servin <bertrand.servin@inrae.fr>
Project-URL: Repository, https://forge.inrae.fr/simon.boitard/snt/
Project-URL: Homepage, https://pypi.org/project/selnetime/
Classifier: Programming Language :: Python :: 3
Classifier: License :: OSI Approved :: MIT License
Classifier: Operating System :: OS Independent
Requires-Python: >=3.7
Requires-Dist: numpy
Requires-Dist: numba>=0.39
Requires-Dist: sympy
Requires-Dist: scipy
Requires-Dist: pyyaml
